DjangoDevKit-1.0.8-py3.7-nspkg.pth
djangodevkit/mediaapp.py
djangodevkit/scripts.py
djangodevkit/serve.py
djangodevkit/utils.py
DjangoDevKit-1.0.8.dist-info/METADATA
DjangoDevKit-1.0.8.dist-info/WHEEL
DjangoDevKit-1.0.8.dist-info/entry_points.txt
DjangoDevKit-1.0.8.dist-info/namespace_packages.txt
DjangoDevKit-1.0.8.dist-info/top_level.txt
DjangoDevKit-1.0.8.dist-info/RECORD
