Metadata-Version: 2.1
Name: DjangoDevKit
Version: 1.0.8
Summary: DjangoDevKit package
Home-page: https://github.com/bearstech/DjangoDevKit
Author: Gael Pasgrimaud
Author-email: gael@gawel.org
License: MIT
Keywords: django
Platform: UNKNOWN
Classifier: Intended Audience :: Developers
Classifier: License :: OSI Approved :: MIT License
Classifier: Topic :: Internet :: WWW/HTTP :: WSGI :: Application
Classifier: Operating System :: POSIX
Classifier: Programming Language :: Python :: 3.5
Classifier: Programming Language :: Python :: 3.7
Requires-Dist: WebOb
Requires-Dist: backlash
Requires-Dist: WebTest
Requires-Dist: IPython
Requires-Dist: waitress
Requires-Dist: django-webtest
Requires-Dist: django-extensions
Requires-Dist: django-debug-toolbar
